network_monitor/__init__.py
network_monitor/cli.py
network_monitor/monitor.py
keepyournetwork-0.1.1.dist-info/LICENSE
keepyournetwork-0.1.1.dist-info/METADATA
keepyournetwork-0.1.1.dist-info/WHEEL
keepyournetwork-0.1.1.dist-info/entry_points.txt
keepyournetwork-0.1.1.dist-info/top_level.txt
keepyournetwork-0.1.1.dist-info/RECORD
