Metadata-Version: 2.2
Name: keepyournetwork
Version: 0.1.1
Summary: A powerful network monitoring and analysis tool with real-time statistics
Home-page: https://github.com/HFerrahoglu/KeepYourNetwork
Author: Hamza Ferrahoğlu
Author-email: hamzaferrahoglu@gmail.com
Project-URL: Bug Tracker, https://github.com/HFerrahoglu/KeepYourNetwork/issues
Project-URL: Documentation, https://github.com/HFerrahoglu/KeepYourNetwork/wiki
Project-URL: Source Code, https://github.com/HFerrahoglu/KeepYourNetwork
Keywords: network,monitoring,bandwidth,traffic,analysis,network-monitor,network-analysis
Classifier: Development Status :: 4 - Beta
Classifier: Environment :: Console
Classifier: Intended Audience :: Developers
Classifier: Intended Audience :: System Administrators
Classifier: Intended Audience :: End Users/Desktop
Classifier: License :: OSI Approved :: MIT License
Classifier: Operating System :: OS Independent
Classifier: Programming Language :: Python :: 3
Classifier: Programming Language :: Python :: 3.7
Classifier: Programming Language :: Python :: 3.8
Classifier: Programming Language :: Python :: 3.9
Classifier: Programming Language :: Python :: 3.10
Classifier: Topic :: System :: Monitoring
Classifier: Topic :: System :: Networking :: Monitoring
Classifier: Topic :: Internet :: Log Analysis
Classifier: Topic :: Utilities
Requires-Python: >=3.7
License-File: LICENSE
Requires-Dist: rich>=13.7.0
Requires-Dist: psutil>=5.9.8
Requires-Dist: colorama>=0.4.6
Dynamic: author
Dynamic: author-email
Dynamic: classifier
Dynamic: description
Dynamic: description-content-type
Dynamic: home-page
Dynamic: keywords
Dynamic: project-url
Dynamic: requires-dist
Dynamic: requires-python
Dynamic: summary
